{
"POSLog": {
"@xmlns" : "http://themall.co.th/retail/sales_transaction",
"@MajorVersion" : "6",
"@xmlns:xsi" : "http://www.w3.org/2001/XMLSchema-instance",
"@xsi:schemaLocation" : "http://themall.co.th/retail/sales_transaction",
"Transaction": [
{
"BusinessUnit":
	{"UnitID":"17KA"},
"WorkstationID":"09101",
"SequenceNumber":"201809110910113464",
"OperatorID":"1111",
"CurrencyCode":"THB",
"Reference": {
	"LocationID":"001",
	"LocationDescription":"Bangkapi Super"},
"RetailTransaction": {
		"@ItemType": "03", 
	"LineItem": [
{
			"Sale":{
				"POSIdentity": {
					"@POSIDType": "EAN",
					"POSItemID": "4902201418782"
					},
				"Description": "NESCAFE KOMIBISAN ME",
				"UnitListPrice": "399.00",
				"RegularSalesUnitPrice": "399.00",
				"ActualSalesUnitPrice": "279.30",
				"ExtendedAmount": "279.30",
				"Quantity": {
					"@UnitOfMeasureCode": "EA",
					"$": "1"
						},
				"Associate": { "AssociateID": "222" },
				"RetailPriceModifier": [
	{
					"SequenceNumber": "1",
					"Amount": {
						"@Action": "Subtract",
						"$": "119.70"
						},
					"PromotionID": "003000000046",
					"Description": "P001 Promotion Supermarket",
					"PromotionArea": "P1",
					"PromotionProfile": "P001"
					}

					],
				"Tax": {
					"@TaxType": "VAT",
					"SequenceNumber": "1",
					"TaxableAmount": {
						"@TaxIncludedInTaxableAmountFlag": "false",
						"$": "261.03"
						},
					"TaxablePercentage": "100.00",
					"Amount": "18.27",
					"Percent": "7",
					"TaxRuleID": "O7"
					},
				"SerialNumber": ""				},
			"SequenceNumber":"1"			},{
			"Tender":{
				"@TenderType": "T004",
				"@SequenceNumber": "1",
				"Amount": {
					"@Currency": "THB",
					"$": "100.00"
					},
				"Voucher":{
					"SerialNumber": "12562",
					"IssuingStoreNumberID": "17KA"
					},
					"Reference": ""
				},
			"SequenceNumber":"2"			},{
			"Tender":{
				"@TenderType": "T001",
				"@SequenceNumber": "2",
				"Amount": {
					"@Currency": "THB",
					"$": "179.25"
					},
					"Reference": ""
				},
			"SequenceNumber":"3"			},{
			"Tender": {
				"@TenderType": "T032",
				"@SequenceNumber": "3",
				"Amount": {
					"@Currency": "THB",
					"$": "0.05"
					}
				},

			"SequenceNumber":"4"			}
		],
	"Customer": { "CustomerID": "" }
	},"BusinessDayDate": "2018-09-11",
"BeginDateTime": "20180911163627",
"EndDateTime": "20180911163659"
}
]
}
}
